{
"type": "FeatureCollection",
"name": "inkwell",
"crs": { "type": "name", "properties": { "name": "urn:ogc:def:crs:OGC:1.3:CRS84" } },
"features": [
{ "type": "Feature", "properties": { "id": null }, "geometry": { "type": "Point", "coordinates": [ -118.491572302032935, 34.005443601549644 ] } }
]
}
